Workbook

Sheet Inputs
B1: ERGO Thailand — Namsing Building Disposal Model
B2: Input Assumptions — edit YELLOW cells only | Blue = hardcoded input | Black = formula
B4: Parameter | C4: Value | D4: Unit / Notes
B5: 1. ASSET BOOK VALUES (YE 2025)
B6: BV — IFRS (YE2025) | C6: 6.1809825e+08 | D6: THB — IFRS carrying value; base for P&L
B7: BV — TFRS / Net Fair Value (YE2025) | C7: 5.9456763e+08 | D7: THB — used for CAR / TCA calculation
B8: Annual Depreciation — IFRS | C8: 5290521.3 | D8: THB/yr — ~50yr useful life
B9: Annual Depreciation — TFRS | C9: 12030292 | D9: THB/yr — ~21.6yr useful life
B10: 2. CAPITAL ADEQUACY (CAR)
B11: TCA — Total Capital Available | C11: 2091 | D11: THB M — from latest OIC filing
B12: TCR — Total Capital Required | C12: 989 | D12: THB M — from latest OIC filing
B13: Current Risk Charge (property) | C13: 56483925 | D13: THB — removed from TCR on disposal
B14: New TCR after disposal (derived) | C14: =(C12*1000000-C13)/1000000 -> 932.51608 | D14: THB M — fixed after disposal
B15: 3. TRANSFER FEE INPUTS
B16: Land area (sq. wah) | C16: 855 | D16: sq. wah — fixed
B17: Land price/sq.wah — pre-2027 | C17: 250000 | D17: THB/sq.wah — current official appraisal
B18: Land price/sq.wah — 2027+ | C18: 250000 | D18: THB/sq.wah — UPDATE when new appraisal published
B19: Building area (sq.m.) | C19: 24109 | D19: sq.m. — fixed
B20: Building price/sq.m. — pre-2027 | C20: 9400 | D20: THB/sq.m. — current official appraisal
B21: Building price/sq.m. — 2027+ | C21: 9400 | D21: THB/sq.m. — UPDATE when new appraisal published
B22: Building dep. rate (% p.a.) | C22: 0.02 | D22: 2% p.a. — Revenue Dept standard
B23: Building age at year 2026 (yrs) | C23: 32 | D23: years — used to derive remaining value
B24: Transfer fee rate | C24: 0.02 | D24: 2% of total appraisal value — fixed by law
B25: → Land appraisal (pre-2027) | C25: =C16*C17 -> 213750000 | D25: Derived: land area x land price per sq.wah (pre-2027)
B26: → Land appraisal (2027+) | C26: =C16*C18 -> 213750000 | D26: Derived: land area x new land price per sq.wah (2027+)
B27: → Building full appraisal value | C27: =C19*C20 -> 226624600 | D27: Derived: building area x building price per sq.m. (pre-2027 rate)
B28: 4. OTHER TRANSACTION COSTS
B29: Specific Business Tax (SBT) | C29: 0.033 | D29: 3.3% of selling price — fixed
B30: Commission rate | C30: 0.03 | D30: 3.0% of selling price — ADJUSTABLE
B31: 5. SELLING PRICE SCENARIOS (THB)
B32: S1 — 665M (High) | C32: 665000000 | D32: THB — edit as needed
B33: S2 — 618M (≈ BV IFRS) | C33: 618000000 | D33: THB — edit as needed
B34: S3 — 550M | C34: 550000000 | D34: THB — edit as needed
B35: S4 — 450M | C35: 450000000 | D35: THB — edit as needed
B36: S5 — 400M | C36: 400000000 | D36: THB — edit as needed
B37: S6 — 300M (Low) | C37: 300000000 | D37: THB — edit as needed
B38: Custom Price | C38: 300000000 | D38: THB — free input
B39: ⚠ Transfer fee base changes from 2027: update 'Land price/sq.wah — 2027+' and 'Building price/sq.m. — 2027+' when new official appraisal is published.
B40: ⚠ Donation scenario not included — see 'Donation Note' sheet for explanation and worked example.

Sheet Analysis
B1: ERGO Thailand — Namsing Building Disposal: Scenario Analysis
B2: All figures in THB unless stated. Formulas link to Inputs sheet — change values there only. Blue = input ref | Black = formula | Green = cross-sheet link
C4: Q2 / 2026 | J4: Q4 / 2026 | Q4: 2027 | X4: 2028 | AE4: 2029 | AL4: 2030 | AS4: 2031
C5: IFRS dep: 0.5yr | TFRS dep: 0.5yr from YE2025 | J5: IFRS dep: 1.0yr | TFRS dep: 1.0yr from YE2025 | Q5: ⚠ New appraisal base from 2027 | X5: ⚠ 2028+: OIC revaluation — TCR may change | AE5: Indicative — confirm OIC treatment | AL5: Indicative — confirm OIC treatment | AS5: Indicative — confirm OIC treatment
B6: Metric | C6: S1 665M | D6: S2 618M | E6: S3 550M | F6: S4 450M | G6: S5 400M | H6: S6 300M | I6: Custom 300M | J6: S1 665M | K6: S2 618M | L6: S3 550M | M6: S4 450M | N6: S5 400M | O6: S6 300M | P6: Custom 300M | Q6: S1 665M | R6: S2 618M | S6: S3 550M | T6: S4 450M | U6: S5 400M | V6: S6 300M | W6: Custom 300M | X6: S1 665M | Y6: S2 618M | Z6: S3 550M | AA6: S4 450M | AB6: S5 400M | AC6: S6 300M | AD6: Custom 300M | AE6: S1 665M | AF6: S2 618M | AG6: S3 550M | AH6: S4 450M | AI6: S5 400M | AJ6: S6 300M | AK6: Custom 300M | AL6: S1 665M | AM6: S2 618M | AN6: S3 550M | AO6: S4 450M | AP6: S5 400M | AQ6: S6 300M | AR6: Custom 300M | AS6: S1 665M | AT6: S2 618M | AU6: S3 550M | AV6: S4 450M | AW6: S5 400M | AX6: S6 300M | AY6: Custom 300M
B7: A. SALE PROCEEDS & TRANSACTION COSTS
B8: Gross Selling Price | C8: =Inputs!$C$32 -> 665000000 | D8: =Inputs!$C$33 -> 618000000 | E8: =Inputs!$C$34 -> 550000000 | F8: =Inputs!$C$35 -> 450000000 | G8: =Inputs!$C$36 -> 400000000 | H8: =Inputs!$C$37 -> 300000000 | I8: =Inputs!$C$38 -> 300000000 | J8: =Inputs!$C$32 -> 665000000 | K8: =Inputs!$C$33 -> 618000000 | L8: =Inputs!$C$34 -> 550000000 | M8: =Inputs!$C$35 -> 450000000 | N8: =Inputs!$C$36 -> 400000000 | O8: =Inputs!$C$37 -> 300000000 | P8: =Inputs!$C$38 -> 300000000 | Q8: =Inputs!$C$32 -> 665000000 | R8: =Inputs!$C$33 -> 618000000 | S8: =Inputs!$C$34 -> 550000000 | T8: =Inputs!$C$35 -> 450000000 | U8: =Inputs!$C$36 -> 400000000 | V8: =Inputs!$C$37 -> 300000000 | W8: =Inputs!$C$38 -> 300000000 | X8: =Inputs!$C$32 -> 665000000 | Y8: =Inputs!$C$33 -> 618000000 | Z8: =Inputs!$C$34 -> 550000000 | AA8: =Inputs!$C$35 -> 450000000 | AB8: =Inputs!$C$36 -> 400000000 | AC8: =Inputs!$C$37 -> 300000000 | AD8: =Inputs!$C$38 -> 300000000 | AE8: =Inputs!$C$32 -> 665000000 | AF8: =Inputs!$C$33 -> 618000000 | AG8: =Inputs!$C$34 -> 550000000 | AH8: =Inputs!$C$35 -> 450000000 | AI8: =Inputs!$C$36 -> 400000000 | AJ8: =Inputs!$C$37 -> 300000000 | AK8: =Inputs!$C$38 -> 300000000 | AL8: =Inputs!$C$32 -> 665000000 | AM8: =Inputs!$C$33 -> 618000000 | AN8: =Inputs!$C$34 -> 550000000 | AO8: =Inputs!$C$35 -> 450000000 | AP8: =Inputs!$C$36 -> 400000000 | AQ8: =Inputs!$C$37 -> 300000000 | AR8: =Inputs!$C$38 -> 300000000 | AS8: =Inputs!$C$32 -> 665000000 | AT8: =Inputs!$C$33 -> 618000000 | AU8: =Inputs!$C$34 -> 550000000 | AV8: =Inputs!$C$35 -> 450000000 | AW8: =Inputs!$C$36 -> 400000000 | AX8: =Inputs!$C$37 -> 300000000 | AY8: =Inputs!$C$38 -> 300000000
B9: Transfer Fee (2% × [land + building appraisal, building net of dep.]) | C9: =-Inputs!$C$24*(Inputs!$C$16*Inputs!$C$17+Inputs!$C$19*Inputs!$C$20*MAX(0,1-Inputs!$C$22*(Inputs!$C$23+0.5))) -> -5861372.2 | D9: =-Inputs!$C$24*(Inputs!$C$16*Inputs!$C$17+Inputs!$C$19*Inputs!$C$20*MAX(0,1-Inputs!$C$22*(Inputs!$C$23+0.5))) -> -5861372.2 | E9: =-Inputs!$C$24*(Inputs!$C$16*Inputs!$C$17+Inputs!$C$19*Inputs!$C$20*MAX(0,1-Inputs!$C$22*(Inputs!$C$23+0.5))) -> -5861372.2 | F9: =-Inputs!$C$24*(Inputs!$C$16*Inputs!$C$17+Inputs!$C$19*Inputs!$C$20*MAX(0,1-Inputs!$C$22*(Inputs!$C$23+0.5))) -> -5861372.2 | G9: =-Inputs!$C$24*(Inputs!$C$16*Inputs!$C$17+Inputs!$C$19*Inputs!$C$20*MAX(0,1-Inputs!$C$22*(Inputs!$C$23+0.5))) -> -5861372.2 | H9: =-Inputs!$C$24*(Inputs!$C$16*Inputs!$C$17+Inputs!$C$19*Inputs!$C$20*MAX(0,1-Inputs!$C$22*(Inputs!$C$23+0.5))) -> -5861372.2 | I9: =-Inputs!$C$24*(Inputs!$C$16*Inputs!$C$17+Inputs!$C$19*Inputs!$C$20*MAX(0,1-Inputs!$C$22*(Inputs!$C$23+0.5))) -> -5861372.2 | J9: =-Inputs!$C$24*(Inputs!$C$16*Inputs!$C$17+Inputs!$C$19*Inputs!$C$20*MAX(0,1-Inputs!$C$22*(Inputs!$C$23+1))) -> -5816047.3 | K9: =-Inputs!$C$24*(Inputs!$C$16*Inputs!$C$17+Inputs!$C$19*Inputs!$C$20*MAX(0,1-Inputs!$C$22*(Inputs!$C$23+1))) -> -5816047.3 | L9: =-Inputs!$C$24*(Inputs!$C$16*Inputs!$C$17+Inputs!$C$19*Inputs!$C$20*MAX(0,1-Inputs!$C$22*(Inputs!$C$23+1))) -> -5816047.3 | M9: =-Inputs!$C$24*(Inputs!$C$16*Inputs!$C$17+Inputs!$C$19*Inputs!$C$20*MAX(0,1-Inputs!$C$22*(Inputs!$C$23+1))) -> -5816047.3 | N9: =-Inputs!$C$24*(Inputs!$C$16*Inputs!$C$17+Inputs!$C$19*Inputs!$C$20*MAX(0,1-Inputs!$C$22*(Inputs!$C$23+1))) -> -5816047.3 | O9: =-Inputs!$C$24*(Inputs!$C$16*Inputs!$C$17+Inputs!$C$19*Inputs!$C$20*MAX(0,1-Inputs!$C$22*(Inputs!$C$23+1))) -> -5816047.3 | P9: =-Inputs!$C$24*(Inputs!$C$16*Inputs!$C$17+Inputs!$C$19*Inputs!$C$20*MAX(0,1-Inputs!$C$22*(Inputs!$C$23+1))) -> -5816047.3 | Q9: =-Inputs!$C$24*(Inputs!$C$16*Inputs!$C$18+Inputs!$C$19*Inputs!$C$21*MAX(0,1-Inputs!$C$22*(Inputs!$C$23+1.5))) -> -5770722.4 | R9: =-Inputs!$C$24*(Inputs!$C$16*Inputs!$C$18+Inputs!$C$19*Inputs!$C$21*MAX(0,1-Inputs!$C$22*(Inputs!$C$23+1.5))) -> -5770722.4 | S9: =-Inputs!$C$24*(Inputs!$C$16*Inputs!$C$18+Inputs!$C$19*Inputs!$C$21*MAX(0,1-Inputs!$C$22*(Inputs!$C$23+1.5))) -> -5770722.4 | T9: =-Inputs!$C$24*(Inputs!$C$16*Inputs!$C$18+Inputs!$C$19*Inputs!$C$21*MAX(0,1-Inputs!$C$22*(Inputs!$C$23+1.5))) -> -5770722.4 | U9: =-Inputs!$C$24*(Inputs!$C$16*Inputs!$C$18+Inputs!$C$19*Inputs!$C$21*MAX(0,1-Inputs!$C$22*(Inputs!$C$23+1.5))) -> -5770722.4 | V9: =-Inputs!$C$24*(Inputs!$C$16*Inputs!$C$18+Inputs!$C$19*Inputs!$C$21*MAX(0,1-Inputs!$C$22*(Inputs!$C$23+1.5))) -> -5770722.4 | W9: =-Inputs!$C$24*(Inputs!$C$16*Inputs!$C$18+Inputs!$C$19*Inputs!$C$21*MAX(0,1-Inputs!$C$22*(Inputs!$C$23+1.5))) -> -5770722.4 | X9: =-Inputs!$C$24*(Inputs!$C$16*Inputs!$C$18+Inputs!$C$19*Inputs!$C$21*MAX(0,1-Inputs!$C$22*(Inputs!$C$23+2.5))) -> -5680072.5 | Y9: =-Inputs!$C$24*(Inputs!$C$16*Inputs!$C$18+Inputs!$C$19*Inputs!$C$21*MAX(0,1-Inputs!$C$22*(Inputs!$C$23+2.5))) -> -5680072.5 | Z9: =-Inputs!$C$24*(Inputs!$C$16*Inputs!$C$18+Inputs!$C$19*Inputs!$C$21*MAX(0,1-Inputs!$C$22*(Inputs!$C$23+2.5))) -> -5680072.5 | AA9: =-Inputs!$C$24*(Inputs!$C$16*Inputs!$C$18+Inputs!$C$19*Inputs!$C$21*MAX(0,1-Inputs!$C$22*(Inputs!$C$23+2.5))) -> -5680072.5 | AB9: =-Inputs!$C$24*(Inputs!$C$16*Inputs!$C$18+Inputs!$C$19*Inputs!$C$21*MAX(0,1-Inputs!$C$22*(Inputs!$C$23+2.5))) -> -5680072.5 | AC9: =-Inputs!$C$24*(Inputs!$C$16*Inputs!$C$18+Inputs!$C$19*Inputs!$C$21*MAX(0,1-Inputs!$C$22*(Inputs!$C$23+2.5))) -> -5680072.5 | AD9: =-Inputs!$C$24*(Inputs!$C$16*Inputs!$C$18+Inputs!$C$19*Inputs!$C$21*MAX(0,1-Inputs!$C$22*(Inputs!$C$23+2.5))) -> -5680072.5 | AE9: =-Inputs!$C$24*(Inputs!$C$16*Inputs!$C$18+Inputs!$C$19*Inputs!$C$21*MAX(0,1-Inputs!$C$22*(Inputs!$C$23+3.5))) -> -5589422.7 | AF9: =-Inputs!$C$24*(Inputs!$C$16*Inputs!$C$18+Inputs!$C$19*Inputs!$C$21*MAX(0,1-Inputs!$C$22*(Inputs!$C$23+3.5))) -> -5589422.7 | AG9: =-Inputs!$C$24*(Inputs!$C$16*Inputs!$C$18+Inputs!$C$19*Inputs!$C$21*MAX(0,1-Inputs!$C$22*(Inputs!$C$23+3.5))) -> -5589422.7 | AH9: =-Inputs!$C$24*(Inputs!$C$16*Inputs!$C$18+Inputs!$C$19*Inputs!$C$21*MAX(0,1-Inputs!$C$22*(Inputs!$C$23+3.5))) -> -5589422.7 | AI9: =-Inputs!$C$24*(Inputs!$C$16*Inputs!$C$18+Inputs!$C$19*Inputs!$C$21*MAX(0,1-Inputs!$C$22*(Inputs!$C$23+3.5))) -> -5589422.7 | AJ9: =-Inputs!$C$24*(Inputs!$C$16*Inputs!$C$18+Inputs!$C$19*Inputs!$C$21*MAX(0,1-Inputs!$C$22*(Inputs!$C$23+3.5))) -> -5589422.7 | AK9: =-Inputs!$C$24*(Inputs!$C$16*Inputs!$C$18+Inputs!$C$19*Inputs!$C$21*MAX(0,1-Inputs!$C$22*(Inputs!$C$23+3.5))) -> -5589422.7 | AL9: =-Inputs!$C$24*(Inputs!$C$16*Inputs!$C$18+Inputs!$C$19*Inputs!$C$21*MAX(0,1-Inputs!$C$22*(Inputs!$C$23+4.5))) -> -5498772.8 | AM9: =-Inputs!$C$24*(Inputs!$C$16*Inputs!$C$18+Inputs!$C$19*Inputs!$C$21*MAX(0,1-Inputs!$C$22*(Inputs!$C$23+4.5))) -> -5498772.8 | AN9: =-Inputs!$C$24*(Inputs!$C$16*Inputs!$C$18+Inputs!$C$19*Inputs!$C$21*MAX(0,1-Inputs!$C$22*(Inputs!$C$23+4.5))) -> -5498772.8 | AO9: =-Inputs!$C$24*(Inputs!$C$16*Inputs!$C$18+Inputs!$C$19*Inputs!$C$21*MAX(0,1-Inputs!$C$22*(Inputs!$C$23+4.5))) -> -5498772.8 | AP9: =-Inputs!$C$24*(Inputs!$C$16*Inputs!$C$18+Inputs!$C$19*Inputs!$C$21*MAX(0,1-Inputs!$C$22*(Inputs!$C$23+4.5))) -> -5498772.8 | AQ9: =-Inputs!$C$24*(Inputs!$C$16*Inputs!$C$18+Inputs!$C$19*Inputs!$C$21*MAX(0,1-Inputs!$C$22*(Inputs!$C$23+4.5))) -> -5498772.8 | AR9: =-Inputs!$C$24*(Inputs!$C$16*Inputs!$C$18+Inputs!$C$19*Inputs!$C$21*MAX(0,1-Inputs!$C$22*(Inputs!$C$23+4.5))) -> -5498772.8 | AS9: =-Inputs!$C$24*(Inputs!$C$16*Inputs!$C$18+Inputs!$C$19*Inputs!$C$21*MAX(0,1-Inputs!$C$22*(Inputs!$C$23+5.5))) -> -5408123 | AT9: =-Inputs!$C$24*(Inputs!$C$16*Inputs!$C$18+Inputs!$C$19*Inputs!$C$21*MAX(0,1-Inputs!$C$22*(Inputs!$C$23+5.5))) -> -5408123 | AU9: =-Inputs!$C$24*(Inputs!$C$16*Inputs!$C$18+Inputs!$C$19*Inputs!$C$21*MAX(0,1-Inputs!$C$22*(Inputs!$C$23+5.5))) -> -5408123 | AV9: =-Inputs!$C$24*(Inputs!$C$16*Inputs!$C$18+Inputs!$C$19*Inputs!$C$21*MAX(0,1-Inputs!$C$22*(Inputs!$C$23+5.5))) -> -5408123 | AW9: =-Inputs!$C$24*(Inputs!$C$16*Inputs!$C$18+Inputs!$C$19*Inputs!$C$21*MAX(0,1-Inputs!$C$22*(Inputs!$C$23+5.5))) -> -5408123 | AX9: =-Inputs!$C$24*(Inputs!$C$16*Inputs!$C$18+Inputs!$C$19*Inputs!$C$21*MAX(0,1-Inputs!$C$22*(Inputs!$C$23+5.5))) -> -5408123 | AY9: =-Inputs!$C$24*(Inputs!$C$16*Inputs!$C$18+Inputs!$C$19*Inputs!$C$21*MAX(0,1-Inputs!$C$22*(Inputs!$C$23+5.5))) -> -5408123
B10: Specific Business Tax (3.3%) | C10: =-Inputs!$C$32*Inputs!$C$29 -> -21945000 | D10: =-Inputs!$C$33*Inputs!$C$29 -> -20394000 | E10: =-Inputs!$C$34*Inputs!$C$29 -> -18150000 | F10: =-Inputs!$C$35*Inputs!$C$29 -> -14850000 | G10: =-Inputs!$C$36*Inputs!$C$29 -> -13200000 | H10: =-Inputs!$C$37*Inputs!$C$29 -> -9900000 | I10: =-Inputs!$C$38*Inputs!$C$29 -> -9900000 | J10: =-Inputs!$C$32*Inputs!$C$29 -> -21945000 | K10: =-Inputs!$C$33*Inputs!$C$29 -> -20394000 | L10: =-Inputs!$C$34*Inputs!$C$29 -> -18150000 | M10: =-Inputs!$C$35*Inputs!$C$29 -> -14850000 | N10: =-Inputs!$C$36*Inputs!$C$29 -> -13200000 | O10: =-Inputs!$C$37*Inputs!$C$29 -> -9900000 | P10: =-Inputs!$C$38*Inputs!$C$29 -> -9900000 | Q10: =-Inputs!$C$32*Inputs!$C$29 -> -21945000 | R10: =-Inputs!$C$33*Inputs!$C$29 -> -20394000 | S10: =-Inputs!$C$34*Inputs!$C$29 -> -18150000 | T10: =-Inputs!$C$35*Inputs!$C$29 -> -14850000 | U10: =-Inputs!$C$36*Inputs!$C$29 -> -13200000 | V10: =-Inputs!$C$37*Inputs!$C$29 -> -9900000 | W10: =-Inputs!$C$38*Inputs!$C$29 -> -9900000 | X10: =-Inputs!$C$32*Inputs!$C$29 -> -21945000 | Y10: =-Inputs!$C$33*Inputs!$C$29 -> -20394000 | Z10: =-Inputs!$C$34*Inputs!$C$29 -> -18150000 | AA10: =-Inputs!$C$35*Inputs!$C$29 -> -14850000 | AB10: =-Inputs!$C$36*Inputs!$C$29 -> -13200000 | AC10: =-Inputs!$C$37*Inputs!$C$29 -> -9900000 | AD10: =-Inputs!$C$38*Inputs!$C$29 -> -9900000 | AE10: =-Inputs!$C$32*Inputs!$C$29 -> -21945000 | AF10: =-Inputs!$C$33*Inputs!$C$29 -> -20394000 | AG10: =-Inputs!$C$34*Inputs!$C$29 -> -18150000 | AH10: =-Inputs!$C$35*Inputs!$C$29 -> -14850000 | AI10: =-Inputs!$C$36*Inputs!$C$29 -> -13200000 | AJ10: =-Inputs!$C$37*Inputs!$C$29 -> -9900000 | AK10: =-Inputs!$C$38*Inputs!$C$29 -> -9900000 | AL10: =-Inputs!$C$32*Inputs!$C$29 -> -21945000 | AM10: =-Inputs!$C$33*Inputs!$C$29 -> -20394000 | AN10: =-Inputs!$C$34*Inputs!$C$29 -> -18150000 | AO10: =-Inputs!$C$35*Inputs!$C$29 -> -14850000 | AP10: =-Inputs!$C$36*Inputs!$C$29 -> -13200000 | AQ10: =-Inputs!$C$37*Inputs!$C$29 -> -9900000 | AR10: =-Inputs!$C$38*Inputs!$C$29 -> -9900000 | AS10: =-Inputs!$C$32*Inputs!$C$29 -> -21945000 | AT10: =-Inputs!$C$33*Inputs!$C$29 -> -20394000 | AU10: =-Inputs!$C$34*Inputs!$C$29 -> -18150000 | AV10: =-Inputs!$C$35*Inputs!$C$29 -> -14850000 | AW10: =-Inputs!$C$36*Inputs!$C$29 -> -13200000 | AX10: =-Inputs!$C$37*Inputs!$C$29 -> -9900000 | AY10: =-Inputs!$C$38*Inputs!$C$29 -> -9900000
B11: Commission Fee (adjustable) | C11: =-Inputs!$C$32*Inputs!$C$30 -> -19950000 | D11: =-Inputs!$C$33*Inputs!$C$30 -> -18540000 | E11: =-Inputs!$C$34*Inputs!$C$30 -> -16500000 | F11: =-Inputs!$C$35*Inputs!$C$30 -> -13500000 | G11: =-Inputs!$C$36*Inputs!$C$30 -> -12000000 | H11: =-Inputs!$C$37*Inputs!$C$30 -> -9000000 | I11: =-Inputs!$C$38*Inputs!$C$30 -> -9000000 | J11: =-Inputs!$C$32*Inputs!$C$30 -> -19950000 | K11: =-Inputs!$C$33*Inputs!$C$30 -> -18540000 | L11: =-Inputs!$C$34*Inputs!$C$30 -> -16500000 | M11: =-Inputs!$C$35*Inputs!$C$30 -> -13500000 | N11: =-Inputs!$C$36*Inputs!$C$30 -> -12000000 | O11: =-Inputs!$C$37*Inputs!$C$30 -> -9000000 | P11: =-Inputs!$C$38*Inputs!$C$30 -> -9000000 | Q11: =-Inputs!$C$32*Inputs!$C$30 -> -19950000 | R11: =-Inputs!$C$33*Inputs!$C$30 -> -18540000 | S11: =-Inputs!$C$34*Inputs!$C$30 -> -16500000 | T11: =-Inputs!$C$35*Inputs!$C$30 -> -13500000 | U11: =-Inputs!$C$36*Inputs!$C$30 -> -12000000 | V11: =-Inputs!$C$37*Inputs!$C$30 -> -9000000 | W11: =-Inputs!$C$38*Inputs!$C$30 -> -9000000 | X11: =-Inputs!$C$32*Inputs!$C$30 -> -19950000 | Y11: =-Inputs!$C$33*Inputs!$C$30 -> -18540000 | Z11: =-Inputs!$C$34*Inputs!$C$30 -> -16500000 | AA11: =-Inputs!$C$35*Inputs!$C$30 -> -13500000 | AB11: =-Inputs!$C$36*Inputs!$C$30 -> -12000000 | AC11: =-Inputs!$C$37*Inputs!$C$30 -> -9000000 | AD11: =-Inputs!$C$38*Inputs!$C$30 -> -9000000 | AE11: =-Inputs!$C$32*Inputs!$C$30 -> -19950000 | AF11: =-Inputs!$C$33*Inputs!$C$30 -> -18540000 | AG11: =-Inputs!$C$34*Inputs!$C$30 -> -16500000 | AH11: =-Inputs!$C$35*Inputs!$C$30 -> -13500000 | AI11: =-Inputs!$C$36*Inputs!$C$30 -> -12000000 | AJ11: =-Inputs!$C$37*Inputs!$C$30 -> -9000000 | AK11: =-Inputs!$C$38*Inputs!$C$30 -> -9000000 | AL11: =-Inputs!$C$32*Inputs!$C$30 -> -19950000 | AM11: =-Inputs!$C$33*Inputs!$C$30 -> -18540000 | AN11: =-Inputs!$C$34*Inputs!$C$30 -> -16500000 | AO11: =-Inputs!$C$35*Inputs!$C$30 -> -13500000 | AP11: =-Inputs!$C$36*Inputs!$C$30 -> -12000000 | AQ11: =-Inputs!$C$37*Inputs!$C$30 -> -9000000 | AR11: =-Inputs!$C$38*Inputs!$C$30 -> -9000000 | AS11: =-Inputs!$C$32*Inputs!$C$30 -> -19950000 | AT11: =-Inputs!$C$33*Inputs!$C$30 -> -18540000 | AU11: =-Inputs!$C$34*Inputs!$C$30 -> -16500000 | AV11: =-Inputs!$C$35*Inputs!$C$30 -> -13500000 | AW11: =-Inputs!$C$36*Inputs!$C$30 -> -12000000 | AX11: =-Inputs!$C$37*Inputs!$C$30 -> -9000000 | AY11: =-Inputs!$C$38*Inputs!$C$30 -> -9000000
B12: Net Sales Proceeds | C12: =C8+C9+C10+C11 -> 6.1724363e+08 | D12: =D8+D9+D10+D11 -> 5.7320463e+08 | E12: =E8+E9+E10+E11 -> 5.0948863e+08 | F12: =F8+F9+F10+F11 -> 4.1578863e+08 | G12: =G8+G9+G10+G11 -> 3.6893863e+08 | H12: =H8+H9+H10+H11 -> 2.7523863e+08 | I12: =I8+I9+I10+I11 -> 2.7523863e+08 | J12: =J8+J9+J10+J11 -> 6.1728895e+08 | ... AY12: =AY8+AY9+AY10+AY11 -> 275691877
B14: B. P&L IMPACT — IFRS
B15: Net Book Value — IFRS (at disposal date) | C15: =Inputs!$C$6-0.5*Inputs!$C$8 -> 6.1545299e+08 | D15: =Inputs!$C$6-0.5*Inputs!$C$8 -> 6.1545299e+08 | E15: =Inputs!$C$6-0.5*Inputs!$C$8 -> 6.1545299e+08 | F15: =Inputs!$C$6-0.5*Inputs!$C$8 -> 6.1545299e+08 | G15: =Inputs!$C$6-0.5*Inputs!$C$8 -> 6.1545299e+08 | H15: =Inputs!$C$6-0.5*Inputs!$C$8 -> 6.1545299e+08 | I15: =Inputs!$C$6-0.5*Inputs!$C$8 -> 6.1545299e+08 | J15: =Inputs!$C$6-1*Inputs!$C$8 -> 6.1280773e+08 | K15: =Inputs!$C$6-1*Inputs!$C$8 -> 6.1280773e+08 | L15: =Inputs!$C$6-1*Inputs!$C$8 -> 6.1280773e+08 | M15: =Inputs!$C$6-1*Inputs!$C$8 -> 6.1280773e+08 | N15: =Inputs!$C$6-1*Inputs!$C$8 -> 6.1280773e+08 | O15: =Inputs!$C$6-1*Inputs!$C$8 -> 6.1280773e+08 | P15: =Inputs!$C$6-1*Inputs!$C$8 -> 6.1280773e+08 | Q15: =Inputs!$C$6-1.5*Inputs!$C$8 -> 6.1016247e+08 | R15: =Inputs!$C$6-1.5*Inputs!$C$8 -> 6.1016247e+08 | S15: =Inputs!$C$6-1.5*Inputs!$C$8 -> 6.1016247e+08 | T15: =Inputs!$C$6-1.5*Inputs!$C$8 -> 6.1016247e+08 | U15: =Inputs!$C$6-1.5*Inputs!$C$8 -> 6.1016247e+08 | V15: =Inputs!$C$6-1.5*Inputs!$C$8 -> 6.1016247e+08 | W15: =Inputs!$C$6-1.5*Inputs!$C$8 -> 6.1016247e+08 | X15: =Inputs!$C$6-2.5*Inputs!$C$8 -> 6.0487195e+08 | Y15: =Inputs!$C$6-2.5*Inputs!$C$8 -> 6.0487195e+08 | Z15: =Inputs!$C$6-2.5*Inputs!$C$8 -> 6.0487195e+08 | AA15: =Inputs!$C$6-2.5*Inputs!$C$8 -> 6.0487195e+08 | AB15: =Inputs!$C$6-2.5*Inputs!$C$8 -> 6.0487195e+08 | AC15: =Inputs!$C$6-2.5*Inputs!$C$8 -> 6.0487195e+08 | AD15: =Inputs!$C$6-2.5*Inputs!$C$8 -> 6.0487195e+08 | AE15: =Inputs!$C$6-3.5*Inputs!$C$8 -> 5.9958143e+08 | AF15: =Inputs!$C$6-3.5*Inputs!$C$8 -> 5.9958143e+08 | AG15: =Inputs!$C$6-3.5*Inputs!$C$8 -> 5.9958143e+08 | AH15: =Inputs!$C$6-3.5*Inputs!$C$8 -> 5.9958143e+08 | AI15: =Inputs!$C$6-3.5*Inputs!$C$8 -> 5.9958143e+08 | AJ15: =Inputs!$C$6-3.5*Inputs!$C$8 -> 5.9958143e+08 | AK15: =Inputs!$C$6-3.5*Inputs!$C$8 -> 5.9958143e+08 | AL15: =Inputs!$C$6-4.5*Inputs!$C$8 -> 5.9429091e+08 | AM15: =Inputs!$C$6-4.5*Inputs!$C$8 -> 5.9429091e+08 | AN15: =Inputs!$C$6-4.5*Inputs!$C$8 -> 5.9429091e+08 | AO15: =Inputs!$C$6-4.5*Inputs!$C$8 -> 5.9429091e+08 | AP15: =Inputs!$C$6-4.5*Inputs!$C$8 -> 5.9429091e+08 | AQ15: =Inputs!$C$6-4.5*Inputs!$C$8 -> 5.9429091e+08 | AR15: =Inputs!$C$6-4.5*Inputs!$C$8 -> 5.9429091e+08 | AS15: =Inputs!$C$6-5.5*Inputs!$C$8 -> 5.8900038e+08 | AT15: =Inputs!$C$6-5.5*Inputs!$C$8 -> 5.8900038e+08 | AU15: =Inputs!$C$6-5.5*Inputs!$C$8 -> 5.8900038e+08 | AV15: =Inputs!$C$6-5.5*Inputs!$C$8 -> 5.8900038e+08 | AW15: =Inputs!$C$6-5.5*Inputs!$C$8 -> 5.8900038e+08 | AX15: =Inputs!$C$6-5.5*Inputs!$C$8 -> 5.8900038e+08 | AY15: =Inputs!$C$6-5.5*Inputs!$C$8 -> 5.8900038e+08
B16: P&L on Disposal (Net Sales − IFRS BV) | C16: =C12-C15 -> 1790636.9 | D16: =D12-D15 -> -42248363 | E16: =E12-E15 -> -1.0596436e+08 | F16: =F12-F15 -> -1.9966436e+08 | G16: =G12-G15 -> -2.4651436e+08 | H16: =H12-H15 -> -3.4021436e+08 | I16: =I12-I15 -> -3.4021436e+08 | J16: =J12-J15 -> 4481222.4 | ... AY16: =AY12-AY15 -> -3.1330851e+08
B17: Note: Tax base for property disposal = max(actual sale price, official appraisal value). The tax payable will not be lower than the appraisal-based calculation, regardless of sale price.
B19: C. CAR IMPACT (Capital Adequacy Ratio = TCA / TCR)
B20: Current CAR (baseline) | C20: =Inputs!$C$11/Inputs!$C$12 -> 2.1142568 | D20: =Inputs!$C$11/Inputs!$C$12 -> 2.1142568 | E20: =Inputs!$C$11/Inputs!$C$12 -> 2.1142568 | F20: =Inputs!$C$11/Inputs!$C$12 -> 2.1142568 | G20: =Inputs!$C$11/Inputs!$C$12 -> 2.1142568 | H20: =Inputs!$C$11/Inputs!$C$12 -> 2.1142568 | I20: =Inputs!$C$11/Inputs!$C$12 -> 2.1142568 | J20: =Inputs!$C$11/Inputs!$C$12 -> 2.1142568 | ... AY20: =Inputs!$C$11/Inputs!$C$12 -> 2.1142568
B21: Net Fair Value — TFRS (at disposal date) | C21: =Inputs!$C$7-0.5*Inputs!$C$9 -> 5.8855248e+08 | D21: =Inputs!$C$7-0.5*Inputs!$C$9 -> 5.8855248e+08 | E21: =Inputs!$C$7-0.5*Inputs!$C$9 -> 5.8855248e+08 | F21: =Inputs!$C$7-0.5*Inputs!$C$9 -> 5.8855248e+08 | G21: =Inputs!$C$7-0.5*Inputs!$C$9 -> 5.8855248e+08 | H21: =Inputs!$C$7-0.5*Inputs!$C$9 -> 5.8855248e+08 | I21: =Inputs!$C$7-0.5*Inputs!$C$9 -> 5.8855248e+08 | J21: =Inputs!$C$7-1*Inputs!$C$9 -> 5.8253734e+08 | K21: =Inputs!$C$7-1*Inputs!$C$9 -> 5.8253734e+08 | L21: =Inputs!$C$7-1*Inputs!$C$9 -> 5.8253734e+08 | M21: =Inputs!$C$7-1*Inputs!$C$9 -> 5.8253734e+08 | N21: =Inputs!$C$7-1*Inputs!$C$9 -> 5.8253734e+08 | O21: =Inputs!$C$7-1*Inputs!$C$9 -> 5.8253734e+08 | P21: =Inputs!$C$7-1*Inputs!$C$9 -> 5.8253734e+08 | Q21: =Inputs!$C$7-1.5*Inputs!$C$9 -> 5.7652219e+08 | R21: =Inputs!$C$7-1.5*Inputs!$C$9 -> 5.7652219e+08 | S21: =Inputs!$C$7-1.5*Inputs!$C$9 -> 5.7652219e+08 | T21: =Inputs!$C$7-1.5*Inputs!$C$9 -> 5.7652219e+08 | U21: =Inputs!$C$7-1.5*Inputs!$C$9 -> 5.7652219e+08 | V21: =Inputs!$C$7-1.5*Inputs!$C$9 -> 5.7652219e+08 | W21: =Inputs!$C$7-1.5*Inputs!$C$9 -> 5.7652219e+08 | X21: =Inputs!$C$7-2.5*Inputs!$C$9 -> 5.644919e+08 | Y21: =Inputs!$C$7-2.5*Inputs!$C$9 -> 5.644919e+08 | Z21: =Inputs!$C$7-2.5*Inputs!$C$9 -> 5.644919e+08 | AA21: =Inputs!$C$7-2.5*Inputs!$C$9 -> 5.644919e+08 | AB21: =Inputs!$C$7-2.5*Inputs!$C$9 -> 5.644919e+08 | AC21: =Inputs!$C$7-2.5*Inputs!$C$9 -> 5.644919e+08 | AD21: =Inputs!$C$7-2.5*Inputs!$C$9 -> 5.644919e+08 | AE21: =Inputs!$C$7-3*Inputs!$C$9 -> 5.5847675e+08 | AF21: =Inputs!$C$7-3*Inputs!$C$9 -> 5.5847675e+08 | AG21: =Inputs!$C$7-3*Inputs!$C$9 -> 5.5847675e+08 | AH21: =Inputs!$C$7-3*Inputs!$C$9 -> 5.5847675e+08 | AI21: =Inputs!$C$7-3*Inputs!$C$9 -> 5.5847675e+08 | AJ21: =Inputs!$C$7-3*Inputs!$C$9 -> 5.5847675e+08 | AK21: =Inputs!$C$7-3*Inputs!$C$9 -> 5.5847675e+08 | AL21: =Inputs!$C$7-4*Inputs!$C$9 -> 5.4644646e+08 | AM21: =Inputs!$C$7-4*Inputs!$C$9 -> 5.4644646e+08 | AN21: =Inputs!$C$7-4*Inputs!$C$9 -> 5.4644646e+08 | AO21: =Inputs!$C$7-4*Inputs!$C$9 -> 5.4644646e+08 | AP21: =Inputs!$C$7-4*Inputs!$C$9 -> 5.4644646e+08 | AQ21: =Inputs!$C$7-4*Inputs!$C$9 -> 5.4644646e+08 | AR21: =Inputs!$C$7-4*Inputs!$C$9 -> 5.4644646e+08 | AS21: =Inputs!$C$7-5*Inputs!$C$9 -> 5.3441617e+08 | AT21: =Inputs!$C$7-5*Inputs!$C$9 -> 5.3441617e+08 | AU21: =Inputs!$C$7-5*Inputs!$C$9 -> 5.3441617e+08 | AV21: =Inputs!$C$7-5*Inputs!$C$9 -> 5.3441617e+08 | AW21: =Inputs!$C$7-5*Inputs!$C$9 -> 5.3441617e+08 | AX21: =Inputs!$C$7-5*Inputs!$C$9 -> 5.3441617e+08 | AY21: =Inputs!$C$7-5*Inputs!$C$9 -> 5.3441617e+08
B22: TCA Change (Net Sales − TFRS Fair Value) | C22: =C12-C21 -> 28691144 | D22: =D12-D21 -> -15347856 | E22: =E12-E21 -> -79063856 | F22: =F12-F21 -> -1.7276386e+08 | G22: =G12-G21 -> -2.1961386e+08 | H22: =H12-H21 -> -3.1331386e+08 | I22: =I12-I21 -> -3.1331386e+08 | J22: =J12-J21 -> 34751615 | ... AY22: =AY12-AY21 -> -2.5872429e+08
B23: New TCA (THB M) | C23: =Inputs!$C$11+C22/1000000 -> 2119.6911 | D23: =Inputs!$C$11+D22/1000000 -> 2075.6521 | E23: =Inputs!$C$11+E22/1000000 -> 2011.9361 | F23: =Inputs!$C$11+F22/1000000 -> 1918.2361 | G23: =Inputs!$C$11+G22/1000000 -> 1871.3861 | H23: =Inputs!$C$11+H22/1000000 -> 1777.6861 | I23: =Inputs!$C$11+I22/1000000 -> 1777.6861 | J23: =Inputs!$C$11+J22/1000000 -> 2125.7516 | ... AY23: =Inputs!$C$11+AY22/1000000 -> 1832.2757
B24: New TCR (THB M) — fixed post-disposal ⚠ Excl. Diversification Benefit → actual CAR gain will be lower | C24: =(Inputs!$C$12*1000000-Inputs!$C$13)/1000000 -> 932.51608 | D24: =(Inputs!$C$12*1000000-Inputs!$C$13)/1000000 -> 932.51608 | E24: =(Inputs!$C$12*1000000-Inputs!$C$13)/1000000 -> 932.51608 | F24: =(Inputs!$C$12*1000000-Inputs!$C$13)/1000000 -> 932.51608 | G24: =(Inputs!$C$12*1000000-Inputs!$C$13)/1000000 -> 932.51608 | H24: =(Inputs!$C$12*1000000-Inputs!$C$13)/1000000 -> 932.51608 | I24: =(Inputs!$C$12*1000000-Inputs!$C$13)/1000000 -> 932.51608 | J24: =(Inputs!$C$12*1000000-Inputs!$C$13)/1000000 -> 932.51608 | ... AY24: =(Inputs!$C$12*1000000-Inputs!$C$13)/1000000 -> 932.51608
B25: New CAR (TCA / TCR) | C25: =C23/C24 -> 2.273088 | D25: =D23/D24 -> 2.2258621 | E25: =E23/E24 -> 2.1575351 | F25: =F23/F24 -> 2.0570542 | G25: =G23/G24 -> 2.0068138 | H25: =H23/H24 -> 1.906333 | I25: =I23/I24 -> 1.906333 | J25: =J23/J24 -> 2.2795871 | ... AY25: =AY23/AY24 -> 1.9648731
B26: CAR Improvement vs Baseline | C26: =C25-C20 -> 0.15883122 | D26: =D25-D20 -> 0.11160523 | E26: =E25-E20 -> 0.043278254 | F26: =F25-F20 -> -0.057202588 | G26: =G25-G20 -> -0.10744301 | H26: =H25-H20 -> -0.20792385 | I26: =I25-I20 -> -0.20792385 | J26: =J25-J20 -> 0.16533027 | ... AY26: =AY25-AY20 -> -0.14938377
B27: ⚠ IMPORTANT NOTES ON CAR: (1) New TCR reduction (฿56.48M) excludes Diversification Benefit — actual CAR improvement will be less than shown above. (2) From 2028: OIC requires property revaluation every 3 years — new appraisal could change risk charge and TCR. Figures for 2028+ are indicative only.

Sheet Donation Note
B1: Donation Scenario — Why It Is Not Included & Tax Explanation
B2: The donation scenario was excluded from the main analysis because the Thai Revenue Code limits property donation deductions to 2% of net profit — making it financially unattractive. This sheet explains the mechanics with an illustrative example.
B4: A. ACCOUNTING TREATMENT ON DONATION (same under TFRS and IFRS)
B5: Journal Entry | C5: Debit | D5: Credit | E5: Amount
B6: Loss on disposal / donation expense | C6: Dr Loss on disposal | E6: Equal to NBV of building
B7: Remove asset from books | D7: Cr Building (NBV) | E7: Equal to NBV of building
B9: P&L Classification | C9: Recorded as 'Loss on disposal' | E9: Full NBV written off
B11: B. TAX TREATMENT — CRITICAL LIMITATION (Thai Revenue Code)
B12: Rule | C12: Donation deduction capped at 2% of net profit before donation deduction
B13: Condition | C13: Company MUST be profitable in the donation year | E13: Donation expense is non-deductible if company is in loss
B14: Excess donation | C14: Amount above 2% cap → added back to taxable income
B16: C. ILLUSTRATIVE EXAMPLE — Why Donation Is Unattractive
B17: ASSUMPTIONS (illustrative)
B18: Company net profit (before donation) | C18: 1000 | D18: THB M
B19: Building NBV donated | C19: 600 | D19: THB M
B20: Tax rate | C20: 0.2 | D20: %
B21: Donation cap (2% × profit) | C21: =C18*0.02 -> 20 | D21: THB M
B22: Allowable donation deduction | C22: =C21 -> 20 | D22: THB M
B23: Excess donation (added back) | C23: =C19-C21 -> 580 | D23: THB M
B25: Taxable income WITHOUT donation | C25: =C18 -> 1000
B26: Tax WITHOUT donation | C26: =C18*C20 -> 200
B28: Adjusted taxable income WITH donation | C28: =C18+C23 -> 1580
B29: (= original profit + excess donation add-back)
B30: Tax WITH donation | C30: =(C18+C23)*C20 -> 316
B32: Additional tax COST from donating | C32: =(C18+C23)*C20-C18*C20 -> 116
B33: NET P&L impact of donation | C33: =-C19+(C18-C23*C20) -> 284
B36: CONCLUSION: Donating a ฿600M building when profit is ฿1,000M results in an EXTRA tax cost of ~฿116M vs not donating. The donation expense is largely non-deductible under Thai law. Scenario excluded from main analysis — sale options S1-S6 are materially better outcomes.
